{"nId": "642", "userId": "59", "type": "0", "title": "", "content": "<div class=\"line\" style=\"color: rgb(0, 0, 0); font-family: monospace; font-size: 13px; white-space: normal;\"><span class=\"html-tag\">&lt;?xml version=\"1.0\" encoding=\"UTF-8\"?&gt;</span></div><div class=\"line\" style=\"color: rgb(0, 0, 0); font-family: monospace; font-size: 13px; white-space: normal;\"><span class=\"html-tag\">&lt;note&gt;</span></div><div class=\"collapsible-content\" style=\"margin-left: 1em; color: rgb(0, 0, 0); font-family: monospace; font-size: 13px; white-space: normal;\"><span class=\"text\"></span><div class=\"line\"><span class=\"html-tag\">&lt;to&gt;</span><span class=\"text\">Tove</span><span class=\"html-tag\">&lt;/to&gt;</span></div><span class=\"text\"></span><div class=\"line\"><span class=\"html-tag\">&lt;from&gt;</span><span class=\"text\">Jani</span><span class=\"html-tag\">&lt;/from&gt;</span></div><span class=\"text\"></span><div class=\"line\"><span class=\"html-tag\">&lt;heading&gt;</span><span class=\"text\">Reminder</span><span class=\"html-tag\">&lt;/heading&gt;</span></div><span class=\"text\"></span><div class=\"line\"><span class=\"html-tag\">&lt;body&gt;</span><span class=\"text\">Don't forget me this weekend!</span><span class=\"html-tag\">&lt;/body&gt;</span></div><span class=\"text\"></span></div><div class=\"line\" style=\"color: rgb(0, 0, 0); font-family: monospace; font-size: 13px; white-space: normal;\"><span class=\"html-tag\">&lt;/note&gt;</span></div>", "upVote": 0, "downVote": 0, "tags": ["HTML", "utf-8"], "favorite": false, "dateCreated": "2017-11-20 03:31:50", "dateModified": "2017-11-20 03:31:50"}